{
    "Annotations": [
        {
            "annotation": "3751",
            "end": 52,
            "start": 48,
            "type": "SBD"
        },
        {
            "annotation": "Titel",
            "end": 58,
            "start": 53,
            "type": "SBD"
        },
        {
            "annotation": "Arbeitnehmers",
            "end": 159,
            "start": 146,
            "type": "SBD"
        },
        {
            "annotation": "Normenketten",
            "end": 172,
            "start": 160,
            "type": "SBD"
        },
        {
            "annotation": "166",
            "end": 205,
            "start": 202,
            "type": "SBD"
        },
        {
            "annotation": "1",
            "end": 258,
            "start": 257,
            "type": "SBD"
        },
        {
            "annotation": "45",
            "end": 271,
            "start": 269,
            "type": "SBD"
        },
        {
            "annotation": "2",
            "end": 329,
            "start": 328,
            "type": "SBD"
        },
        {
            "annotation": "1",
            "end": 349,
            "start": 348,
            "type": "SBD"
        },
        {
            "annotation": "Leitsätze",
            "end": 359,
            "start": 350,
            "type": "SBD"
        },
        {
            "annotation": "erweist",
            "end": 801,
            "start": 794,
            "type": "SBD"
        },
        {
            "annotation": ")",
            "end": 811,
            "start": 810,
            "type": "SBD"
        },
        {
            "annotation": ")",
            "end": 837,
            "start": 836,
            "type": "SBD"
        },
        {
            "annotation": "aus",
            "end": 1007,
            "start": 1004,
            "type": "SBD"
        },
        {
            "annotation": ")",
            "end": 1257,
            "start": 1256,
            "type": "SBD"
        },
        {
            "annotation": ")",
            "end": 1284,
            "start": 1283,
            "type": "SBD"
        },
        {
            "annotation": "Schlagworte",
            "end": 1296,
            "start": 1285,
            "type": "SBD"
        },
        {
            "annotation": "Tarifvertrag",
            "end": 1638,
            "start": 1626,
            "type": "SBD"
        },
        {
            "annotation": "Fundstelle",
            "end": 1649,
            "start": 1639,
            "type": "SBD"
        },
        {
            "annotation": "9112",
            "end": 1668,
            "start": 1664,
            "type": "SBD"
        },
        {
            "annotation": "Tenor",
            "end": 1674,
            "start": 1669,
            "type": "SBD"
        },
        {
            "annotation": "angeordnet",
            "end": 1766,
            "start": 1756,
            "type": "SBD"
        },
        {
            "annotation": "Verfahrens",
            "end": 1823,
            "start": 1813,
            "type": "SBD"
        },
        {
            "annotation": "festgesetzt",
            "end": 1875,
            "start": 1864,
            "type": "SBD"
        },
        {
            "annotation": "verbunden",
            "end": 2030,
            "start": 2021,
            "type": "SBD"
        },
        {
            "annotation": "beigeordnet",
            "end": 2131,
            "start": 2120,
            "type": "SBD"
        },
        {
            "annotation": "Gründe",
            "end": 2139,
            "start": 2133,
            "type": "SBD"
        },
        {
            "annotation": "I",
            "end": 2141,
            "start": 2140,
            "type": "SBD"
        },
        {
            "annotation": "1",
            "end": 2144,
            "start": 2143,
            "type": "SBD"
        },
        {
            "annotation": "ein",
            "end": 2355,
            "start": 2352,
            "type": "SBD"
        },
        {
            "annotation": "2",
            "end": 2358,
            "start": 2357,
            "type": "SBD"
        },
        {
            "annotation": "Arbeitsverhältnisse",
            "end": 2437,
            "start": 2418,
            "type": "SBD"
        },
        {
            "annotation": "beschäftigt",
            "end": 2659,
            "start": 2648,
            "type": "SBD"
        },
        {
            "annotation": "befristet",
            "end": 2696,
            "start": 2687,
            "type": "SBD"
        },
        {
            "annotation": "beschäftigt",
            "end": 2838,
            "start": 2827,
            "type": "SBD"
        },
        {
            "annotation": "beendet",
            "end": 2908,
            "start": 2901,
            "type": "SBD"
        },
        {
            "annotation": "wahr",
            "end": 3033,
            "start": 3029,
            "type": "SBD"
        },
        {
            "annotation": "auf",
            "end": 3128,
            "start": 3125,
            "type": "SBD"
        },
        {
            "annotation": "beendet",
            "end": 3247,
            "start": 3240,
            "type": "SBD"
        },
        {
            "annotation": "Vollzeit",
            "end": 3362,
            "start": 3354,
            "type": "SBD"
        },
        {
            "annotation": "3",
            "end": 3365,
            "start": 3364,
            "type": "SBD"
        },
        {
            "annotation": "Leistungen",
            "end": 3529,
            "start": 3519,
            "type": "SBD"
        },
        {
            "annotation": "II",
            "end": 3642,
            "start": 3640,
            "type": "SBD"
        },
        {
            "annotation": "werden",
            "end": 3866,
            "start": 3860,
            "type": "SBD"
        },
        {
            "annotation": "Familienhilfe",
            "end": 3951,
            "start": 3938,
            "type": "SBD"
        },
        {
            "annotation": "4",
            "end": 3954,
            "start": 3953,
            "type": "SBD"
        },
        {
            "annotation": "Schulter",
            "end": 4034,
            "start": 4026,
            "type": "SBD"
        },
        {
            "annotation": "vor",
            "end": 4223,
            "start": 4220,
            "type": "SBD"
        },
        {
            "annotation": "statt",
            "end": 4338,
            "start": 4333,
            "type": "SBD"
        },
        {
            "annotation": "Anschlussheilbehandlung",
            "end": 4464,
            "start": 4441,
            "type": "SBD"
        },
        {
            "annotation": "5",
            "end": 4467,
            "start": 4466,
            "type": "SBD"
        },
        {
            "annotation": "zuerkannt",
            "end": 4653,
            "start": 4644,
            "type": "SBD"
        },
        {
            "annotation": ")",
            "end": 5043,
            "start": 5042,
            "type": "SBD"
        },
        {
            "annotation": "10",
            "end": 5046,
            "start": 5044,
            "type": "SBD"
        },
        {
            "annotation": "kann",
            "end": 5273,
            "start": 5269,
            "type": "SBD"
        },
        {
            "annotation": "vermindert",
            "end": 5338,
            "start": 5328,
            "type": "SBD"
        },
        {
            "annotation": "habe",
            "end": 5477,
            "start": 5473,
            "type": "SBD"
        },
        {
            "annotation": "bewältigen",
            "end": 5542,
            "start": 5532,
            "type": "SBD"
        },
        {
            "annotation": "lindern",
            "end": 5683,
            "start": 5676,
            "type": "SBD"
        },
        {
            "annotation": "11",
            "end": 5687,
            "start": 5685,
            "type": "SBD"
        },
        {
            "annotation": "könnten",
            "end": 5842,
            "start": 5835,
            "type": "SBD"
        },
        {
            "annotation": "verändere",
            "end": 5936,
            "start": 5927,
            "type": "SBD"
        },
        {
            "annotation": "12",
            "end": 5940,
            "start": 5938,
            "type": "SBD"
        },
        {
            "annotation": ")",
            "end": 6149,
            "start": 6148,
            "type": "SBD"
        },
        {
            "annotation": ")",
            "end": 6443,
            "start": 6442,
            "type": "SBD"
        },
        {
            "annotation": ")",
            "end": 6521,
            "start": 6520,
            "type": "SBD"
        },
        {
            "annotation": ")",
            "end": 6611,
            "start": 6610,
            "type": "SBD"
        },
        {
            "annotation": "13",
            "end": 6615,
            "start": 6613,
            "type": "SBD"
        },
        {
            "annotation": "nehme",
            "end": 6891,
            "start": 6886,
            "type": "SBD"
        },
        {
            "annotation": "14",
            "end": 6895,
            "start": 6893,
            "type": "SBD"
        },
        {
            "annotation": "und",
            "end": 7119,
            "start": 7116,
            "type": "SBD"
        },
        {
            "annotation": "16",
            "end": 7122,
            "start": 7120,
            "type": "SBD"
        },
        {
            "annotation": "beizuordnen",
            "end": 7235,
            "start": 7224,
            "type": "SBD"
        },
        {
            "annotation": "17",
            "end": 7239,
            "start": 7237,
            "type": "SBD"
        },
        {
            "annotation": "Arbeitnehmerin",
            "end": 7313,
            "start": 7299,
            "type": "SBD"
        },
        {
            "annotation": "bemüht",
            "end": 7385,
            "start": 7379,
            "type": "SBD"
        },
        {
            "annotation": "Arbeitnehmerfreizügigkeitsrecht",
            "end": 7469,
            "start": 7438,
            "type": "SBD"
        },
        {
            "annotation": "arbeitslos",
            "end": 7563,
            "start": 7553,
            "type": "SBD"
        },
        {
            "annotation": "2018",
            "end": 8160,
            "start": 8156,
            "type": "SBD"
        },
        {
            "annotation": "18",
            "end": 8164,
            "start": 8162,
            "type": "SBD"
        },
        {
            "annotation": "bemüht",
            "end": 8278,
            "start": 8272,
            "type": "SBD"
        },
        {
            "annotation": "vor",
            "end": 8359,
            "start": 8356,
            "type": "SBD"
        },
        {
            "annotation": "musste",
            "end": 8491,
            "start": 8485,
            "type": "SBD"
        },
        {
            "annotation": "gewesen",
            "end": 8623,
            "start": 8616,
            "type": "SBD"
        },
        {
            "annotation": "19",
            "end": 8627,
            "start": 8625,
            "type": "SBD"
        },
        {
            "annotation": "abzulehnen",
            "end": 8718,
            "start": 8708,
            "type": "SBD"
        },
        {
            "annotation": "21",
            "end": 8722,
            "start": 8720,
            "type": "SBD"
        },
        {
            "annotation": "genommen",
            "end": 8844,
            "start": 8836,
            "type": "SBD"
        },
        {
            "annotation": "II",
            "end": 8848,
            "start": 8846,
            "type": "SBD"
        },
        {
            "annotation": "I",
            "end": 8851,
            "start": 8850,
            "type": "SBD"
        },
        {
            "annotation": "22",
            "end": 8855,
            "start": 8853,
            "type": "SBD"
        },
        {
            "annotation": "begründet",
            "end": 8893,
            "start": 8884,
            "type": "SBD"
        },
        {
            "annotation": "23",
            "end": 8897,
            "start": 8895,
            "type": "SBD"
        },
        {
            "annotation": "hat",
            "end": 9066,
            "start": 9063,
            "type": "SBD"
        },
        {
            "annotation": "24",
            "end": 9070,
            "start": 9068,
            "type": "SBD"
        },
        {
            "annotation": "begründet",
            "end": 9103,
            "start": 9094,
            "type": "SBD"
        },
        {
            "annotation": "25",
            "end": 9107,
            "start": 9105,
            "type": "SBD"
        },
        {
            "annotation": "VwGO",
            "end": 9264,
            "start": 9260,
            "type": "SBD"
        },
        {
            "annotation": "rechtfertigt",
            "end": 9411,
            "start": 9399,
            "type": "SBD"
        },
        {
            "annotation": "bewirkt",
            "end": 9575,
            "start": 9568,
            "type": "SBD"
        },
        {
            "annotation": ")",
            "end": 9809,
            "start": 9808,
            "type": "SBD"
        },
        {
            "annotation": "bewusst",
            "end": 9895,
            "start": 9888,
            "type": "SBD"
        },
        {
            "annotation": "hielt",
            "end": 10047,
            "start": 10042,
            "type": "SBD"
        },
        {
            "annotation": "Kassen",
            "end": 10236,
            "start": 10230,
            "type": "SBD"
        },
        {
            "annotation": "tragen",
            "end": 10302,
            "start": 10296,
            "type": "SBD"
        },
        {
            "annotation": "26",
            "end": 10306,
            "start": 10304,
            "type": "SBD"
        },
        {
            "annotation": "wiederherstellen",
            "end": 10490,
            "start": 10474,
            "type": "SBD"
        },
        {
            "annotation": "Klage",
            "end": 10814,
            "start": 10809,
            "type": "SBD"
        },
        {
            "annotation": "Hauptsacheverfahrens",
            "end": 10908,
            "start": 10888,
            "type": "SBD"
        },
        {
            "annotation": "zurück",
            "end": 11175,
            "start": 11169,
            "type": "SBD"
        },
        {
            "annotation": "Vollziehung",
            "end": 11337,
            "start": 11326,
            "type": "SBD"
        },
        {
            "annotation": "Interessenabwägung",
            "end": 11458,
            "start": 11440,
            "type": "SBD"
        },
        {
            "annotation": "27",
            "end": 11462,
            "start": 11460,
            "type": "SBD"
        },
        {
            "annotation": "begründet",
            "end": 11596,
            "start": 11587,
            "type": "SBD"
        },
        {
            "annotation": "28",
            "end": 11600,
            "start": 11598,
            "type": "SBD"
        },
        {
            "annotation": "vor",
            "end": 11701,
            "start": 11698,
            "type": "SBD"
        },
        {
            "annotation": "erweist",
            "end": 12147,
            "start": 12140,
            "type": "SBD"
        },
        {
            "annotation": "29",
            "end": 12151,
            "start": 12149,
            "type": "SBD"
        },
        {
            "annotation": "freizügigkeitsberechtigt",
            "end": 12253,
            "start": 12229,
            "type": "SBD"
        },
        {
            "annotation": ")",
            "end": 12553,
            "start": 12552,
            "type": "SBD"
        },
        {
            "annotation": "30",
            "end": 12557,
            "start": 12555,
            "type": "SBD"
        },
        {
            "annotation": "nach",
            "end": 12709,
            "start": 12705,
            "type": "SBD"
        },
        {
            "annotation": "Arbeitnehmerin",
            "end": 12808,
            "start": 12794,
            "type": "SBD"
        },
        {
            "annotation": "31",
            "end": 12812,
            "start": 12810,
            "type": "SBD"
        },
        {
            "annotation": "dar",
            "end": 12994,
            "start": 12991,
            "type": "SBD"
        },
        {
            "annotation": ")",
            "end": 13193,
            "start": 13192,
            "type": "SBD"
        },
        {
            "annotation": "werden",
            "end": 13676,
            "start": 13670,
            "type": "SBD"
        },
        {
            "annotation": "sichert",
            "end": 13975,
            "start": 13968,
            "type": "SBD"
        },
        {
            "annotation": "32",
            "end": 13979,
            "start": 13977,
            "type": "SBD"
        },
        {
            "annotation": "stehen",
            "end": 14142,
            "start": 14136,
            "type": "SBD"
        },
        {
            "annotation": "dürfte",
            "end": 14312,
            "start": 14306,
            "type": "SBD"
        },
        {
            "annotation": "war",
            "end": 14565,
            "start": 14562,
            "type": "SBD"
        },
        {
            "annotation": "33",
            "end": 14569,
            "start": 14567,
            "type": "SBD"
        },
        {
            "annotation": "ausübt",
            "end": 14911,
            "start": 14905,
            "type": "SBD"
        },
        {
            "annotation": "aus",
            "end": 15088,
            "start": 15085,
            "type": "SBD"
        },
        {
            "annotation": ")",
            "end": 15406,
            "start": 15405,
            "type": "SBD"
        },
        {
            "annotation": "war",
            "end": 15655,
            "start": 15652,
            "type": "SBD"
        },
        {
            "annotation": "angetreten",
            "end": 15799,
            "start": 15789,
            "type": "SBD"
        },
        {
            "annotation": "beendet",
            "end": 15920,
            "start": 15913,
            "type": "SBD"
        },
        {
            "annotation": "hat",
            "end": 16144,
            "start": 16141,
            "type": "SBD"
        },
        {
            "annotation": "ausübte",
            "end": 16300,
            "start": 16293,
            "type": "SBD"
        },
        {
            "annotation": "Vollzeit",
            "end": 16401,
            "start": 16393,
            "type": "SBD"
        },
        {
            "annotation": "gekündigt",
            "end": 16530,
            "start": 16521,
            "type": "SBD"
        },
        {
            "annotation": "gearbeitet",
            "end": 16602,
            "start": 16592,
            "type": "SBD"
        },
        {
            "annotation": "hat",
            "end": 16732,
            "start": 16729,
            "type": "SBD"
        },
        {
            "annotation": "beziehen",
            "end": 17077,
            "start": 17069,
            "type": "SBD"
        },
        {
            "annotation": "34",
            "end": 17081,
            "start": 17079,
            "type": "SBD"
        },
        {
            "annotation": "hat",
            "end": 17240,
            "start": 17237,
            "type": "SBD"
        },
        {
            "annotation": "besteht",
            "end": 17470,
            "start": 17463,
            "type": "SBD"
        },
        {
            "annotation": "gelten",
            "end": 17626,
            "start": 17620,
            "type": "SBD"
        },
        {
            "annotation": ")",
            "end": 17958,
            "start": 17957,
            "type": "SBD"
        },
        {
            "annotation": "arbeitsunfähig",
            "end": 18133,
            "start": 18119,
            "type": "SBD"
        },
        {
            "annotation": "bescheinigt",
            "end": 18193,
            "start": 18182,
            "type": "SBD"
        },
        {
            "annotation": "kann",
            "end": 18480,
            "start": 18476,
            "type": "SBD"
        },
        {
            "annotation": "vermeiden",
            "end": 18589,
            "start": 18580,
            "type": "SBD"
        },
        {
            "annotation": "sei",
            "end": 18700,
            "start": 18697,
            "type": "SBD"
        },
        {
            "annotation": "Schmerzen",
            "end": 18771,
            "start": 18762,
            "type": "SBD"
        },
        {
            "annotation": "lindern",
            "end": 18912,
            "start": 18905,
            "type": "SBD"
        },
        {
            "annotation": "können",
            "end": 19018,
            "start": 19012,
            "type": "SBD"
        },
        {
            "annotation": "verändere",
            "end": 19115,
            "start": 19106,
            "type": "SBD"
        },
        {
            "annotation": "positiv",
            "end": 19189,
            "start": 19182,
            "type": "SBD"
        },
        {
            "annotation": "vermindert",
            "end": 19254,
            "start": 19244,
            "type": "SBD"
        },
        {
            "annotation": "erhalten",
            "end": 19444,
            "start": 19436,
            "type": "SBD"
        },
        {
            "annotation": "35",
            "end": 19448,
            "start": 19446,
            "type": "SBD"
        },
        {
            "annotation": "arbeitssuchend",
            "end": 19591,
            "start": 19577,
            "type": "SBD"
        },
        {
            "annotation": "vorgelegt",
            "end": 19665,
            "start": 19656,
            "type": "SBD"
        },
        {
            "annotation": "36",
            "end": 19669,
            "start": 19667,
            "type": "SBD"
        },
        {
            "annotation": "konnte",
            "end": 19958,
            "start": 19952,
            "type": "SBD"
        },
        {
            "annotation": "beziehen",
            "end": 20142,
            "start": 20134,
            "type": "SBD"
        },
        {
            "annotation": "37",
            "end": 20146,
            "start": 20144,
            "type": "SBD"
        },
        {
            "annotation": "werden",
            "end": 20257,
            "start": 20251,
            "type": "SBD"
        },
        {
            "annotation": "EUR",
            "end": 20389,
            "start": 20386,
            "type": "SBD"
        },
        {
            "annotation": "kann",
            "end": 20568,
            "start": 20564,
            "type": "SBD"
        },
        {
            "annotation": "monatlich",
            "end": 20722,
            "start": 20713,
            "type": "SBD"
        },
        {
            "annotation": "absehbar",
            "end": 20841,
            "start": 20833,
            "type": "SBD"
        },
        {
            "annotation": "hätten",
            "end": 20990,
            "start": 20984,
            "type": "SBD"
        },
        {
            "annotation": "nicht",
            "end": 21210,
            "start": 21205,
            "type": "SBD"
        },
        {
            "annotation": "handelt",
            "end": 21391,
            "start": 21384,
            "type": "SBD"
        },
        {
            "annotation": ")",
            "end": 21627,
            "start": 21626,
            "type": "SBD"
        },
        {
            "annotation": "38",
            "end": 21631,
            "start": 21629,
            "type": "SBD"
        },
        {
            "annotation": "beziehen",
            "end": 21772,
            "start": 21764,
            "type": "SBD"
        },
        {
            "annotation": "39",
            "end": 21776,
            "start": 21774,
            "type": "SBD"
        },
        {
            "annotation": "Arbeitnehmerfreizügigkeitsrechts",
            "end": 21879,
            "start": 21847,
            "type": "SBD"
        },
        {
            "annotation": "genießt",
            "end": 22040,
            "start": 22033,
            "type": "SBD"
        },
        {
            "annotation": "einzuschränken",
            "end": 22234,
            "start": 22220,
            "type": "SBD"
        },
        {
            "annotation": "Richtlinie",
            "end": 22294,
            "start": 22284,
            "type": "SBD"
        },
        {
            "annotation": "40",
            "end": 22298,
            "start": 22296,
            "type": "SBD"
        },
        {
            "annotation": "ab",
            "end": 22579,
            "start": 22577,
            "type": "SBD"
        },
        {
            "annotation": "II",
            "end": 22583,
            "start": 22581,
            "type": "SBD"
        },
        {
            "annotation": "41",
            "end": 22587,
            "start": 22585,
            "type": "SBD"
        },
        {
            "annotation": "VwGO",
            "end": 22639,
            "start": 22635,
            "type": "SBD"
        },
        {
            "annotation": "III",
            "end": 22644,
            "start": 22641,
            "type": "SBD"
        },
        {
            "annotation": "42",
            "end": 22648,
            "start": 22646,
            "type": "SBD"
        },
        {
            "annotation": "Verwaltungsgerichtsbarkeit",
            "end": 22812,
            "start": 22786,
            "type": "SBD"
        },
        {
            "annotation": "IV",
            "end": 22816,
            "start": 22814,
            "type": "SBD"
        },
        {
            "annotation": "43",
            "end": 22820,
            "start": 22818,
            "type": "SBD"
        },
        {
            "annotation": "ZPO",
            "end": 23155,
            "start": 23152,
            "type": "SBD"
        }
    ],
    "Text": "VG München, Beschluss v. 07.05.2019 – M 25 S 18.3751\nTitel:\nErfolgreicher Eilrechtsschutz gegen Feststellung des Verlusts der Freizügigkeit eines\nArbeitnehmers\nNormenketten:\nVwGO § 80 Abs. 4, Abs. 5, § 166\nFreizügG/EU § 2 Abs. 1, Abs. 3 S. 1, § 5 Abs. 4 S. 1\nAEUV Art. 45\nRL 2004/38/EG Art. 17 Abs. 1 S. 2, Art. 24 Abs. 1, Abs. 2\nSGB VIII § 1 Abs. 1\nLeitsätze:\n1. Der Verlust des Freizügigkeitsrechts kann nach nach § 5 Abs. 4 S. 1 FreizügG/EU festgestellt\nwerden, wenn die Voraussetzungen des Rechts nach § 2 Abs. 1 FreizügG/EU innerhalb von 5 Jahren\nnach Begründung des ständigen rechtmäßigen Aufenthalts im Bundesgebiet entfallen sind, (von\nAnfang an) nicht vorliegen (Anschluss an BVerwG BeckRS 2015, 50492) oder sich die Berufung auf\ndie Arbeitnehmerfreizügigkeit als rechtsmissbräuchlich erweist. (Rn. 28) (redaktioneller Leitsatz)\n2. Der Umstand, dass im Rahmen eines Beschäftigungsverhältnisses nur weniger Arbeitsstunden\ngeleistet werden, schließt die Arbeitnehmereigenschaft nicht zwangsläufig aus. Es spielen auch\nAspekte wie der Anspruch auf bezahlten Urlaub, die Geltung von Lohnfortzahlung im Krankheitsfall,\ndie Anwendung des Tarifvertrages oder auch die Dauer des Beschäftigungsverhältnisses eine Rolle\n(Anschluss an EuGH BeckRS 2014, 80531). (redaktioneller Leitsatz)\nSchlagworte:\nProzesskostenhilfe (bewilligt), Begriff des Arbeitnehmers, Unangemessener Sozialhilfebezug,\nGesundheitszustand, Ausländer, Rechtsmissbrauch, Arbeitsunfähigkeitsbescheinigung, Krankheitsfall,\nVerlustfeststellung, Freizügigkeitsrecht, Beschäftigungsverhältnis, Arbeitsstunden, bezahlter Urlaub,\nLohnfortzahlung im Krankheitsfall, Tarifvertrag\nFundstelle:\nBeckRS 2019, 9112\nTenor\nI. Die aufschiebende Wirkung der Klage gegen den Bescheid vom 10. Juli 2018 wird angeordnet.\nII. Die Antragsgegnerin trägt die Kosten des Verfahrens.\nIII. Der Streitwert wird auf 7.500 EUR festgesetzt.\nIV. Die Verfahren M 25 K 18.3750 und M 25 S 18.3751 werden zur gemeinsamen Entscheidung über die\nAnträge auf Bewilligung von Prozesskostenhilfe verbunden.\nDen Klägern und Antragstellern wird Prozesskostenhilfe bewilligt und Rechtsanwältin ... beigeordnet.\nGründe\nI.\n1\nDie am ... 1977 geborene Antragstellerin zu 1) ist spanische Staatsangehörige und reiste am 11. Juli 2014\nzusammen mit ihren beiden Kindern, den Antragstellern zu 2) und 3) in die Bundesrepublik Deutschland ein.\n2\nDie Antragstellerin zu 1) hatte seit der Einreise folgende Arbeitsverhältnisse: Vom 20. November 2014 bis\n19. November 2016 war die Antragstellerin zu 1) als Reinigungskraft bei der Firma … (durch\nVerschmelzung später bei Firma … …) mit durchschnittlich 2 Stunden in der Woche geringfügig beschäftigt.\nDas Arbeitsverhältnis war befristet. Vom 1. Juni 2015 bis 24. Juli 2015 war die Antragstellerin zusätzlich bei\nder Firma … mit einer Wochenarbeitszeit von 30 Stunden beschäftigt. Das Arbeitsverhältnis wurde durch\nKündigung des Arbeitgebers beendet. Vom 21. Juli 2015 bis 10. März 2016 nahm die Antragstellerin eine\nTätigkeit als Haushaltshilfe in einem Privathaushalt wahr. Am 11. März 2016 nahm die Antragstellerin eine\nTätigkeit bei der Firma Enzian in Vollzeit auf. Das Arbeitsverhältnis wurde durch Kündigung von Seiten des\nArbeitsgebers in der Probezeit zum 7. Oktober 2016 beendet. Seit 1. Dezember 2018 arbeitet die\nAntragstellerin bei der Firma … Pflegedienst mit Seniorenbetreuung in Vollzeit.\n3\nSeit Oktober 2014 erhielten die Antragsteller vom Jobcenter der Stadt Ingolstadt Leistungen nach dem SGB\nII im zeitlichen Wechsel aufstockend bzw. volle Leistungen. In den Monaten Juli 2015 und August bis\nOktober 2016 bezogen die Antragsteller keine Leistungen nach dem SGB II. Der Antragsteller zu 2) befand\nsich von Juli 2016 bis 5. Februar 2019 in einer Jugendhilfeeinrichtung, deren Kosten i.H.v. zunächst 4.500\nEUR, ab August 2017 i.H.v. 5.500 EUR pro Monat von der Jugendhilfe übernommen werden. Daneben\nerhält die Familie seit 28. Juni 2018 eine sozialpädagogische Familienhilfe.\n4\nDie Antragstellerin zu 1) leidet unter anderem an einer Verletzung der Schulter. Sie legte\nArbeitsunfähigkeitsbescheinigungen für die Zeiträume 7. März 2017 - 3. April 2017, 2. Juni 2017 - 2. Juli\n2017, 7. Juli 2017 - 30. Juli 2017 und 4. Juni 2018 - 15. Juni 2018 vor. In der Zeit vom 29. Mai 2017 bis 1.\nJuni 2017 fand eine Operation mit anschließendem stationärem Aufenthalt statt. Im Anschluss daran befand\nsich die Antragstellerin zu 1) vom 16. Juni 2017 bis 6. Juli 2017 in einer Anschlussheilbehandlung.\n5\nMit Bescheid des Zentrums Bayern Familie und Soziales, Region Oberfranken, Versorgungsamt, vom 19.\nJanuar 2018 wurde der Antragstellerin zu 1) ein Grad der Behinderung von 40% zuerkannt. Dem Bescheid\nliegen folgende Erkrankungen zu Grund:\n6\n- seelische Störung Depression, psychovegetative Störungen (Einzel GdB: 30)\n7\n- Bronchialasthma (Einzel GdB: 20)\n8\n- Funktionsbehinderung der Wirbelsäule, degenerative Veränderungen, operierter Bandscheibenschaden,\nVersteifung von Wirbelsäulen-Abschnitten (Einzel-GdB: 20)\n9\n- Funktionsbehinderung der Schultergelenke (Einzel-GdB: 10)\n10\nAus dem amtsärztlichen Gutachten zur Beurteilung der Arbeits-/Erwerbsfähigkeit vom 30. April 2018 (Bl. 42\nder Gerichtsakte) geht hervor, dass die Antragstellerin zu 1) einer Tätigkeit von täglich 3 bis 6 Stunden\nnachgehen kann. Die Leistungsfähigkeit sei für die nächsten 6 Monate vermindert. Die Antragstellerin zu 1)\nleide an einer Erkrankung des Bewegungsapparates, weswegen sie bei den meisten Bewegungen starke\nSchmerzen habe. Den Haushalt könne sie langsam und mit vielen Pausen bewältigen. Sie sei in\nkontinuierlicher orthopädischer und neurochirurgischer Behandlung und zeige viel Eigeninitiative, um ihre\nBeschwerden zu lindern.\n11\nDie Erkrankung sei nicht vollständig heilbar, es blieben aber noch ein paar Behandlungsoptionen, die eine\nSteigerung der Arbeitsfähigkeit bewirken könnten. Es bleibe abzuwarten, wie sich das Beschwerdebild unter\nden angestrebten Therapien verändere.\n12\nNach Anhörung der Antragsteller stellte die Antragsgegnerin mit Bescheid vom 10. Juli 2018 den Verlust\ndes Rechts der Antragsteller auf Einreise und Aufenthalt in der Bundesrepublik Deutschland fest (Ziff. 1).\nSie forderte die Antragsteller zur Ausreise innerhalb eines Monats auf und drohte ihnen für den Fall des\nNichteinhaltens dieser Frist die Abschiebung nach Spanien oder einen anderen Staat an, in den die\nAntragsteller einreisen dürfen oder der zu ihrer Rückübernahme verpflichtet ist (Ziff. 2). Die Wiedereinreise\nwurde für einen Zeitraum von 3 Jahren untersagt (Ziff. 3). Gleichzeitig ordnete sie die sofortige Vollziehung\nder Nr. 1 des Bescheides an (Ziff. 6).\n13\nDie Antragsgegnerin führte zur Begründung im Wesentlichen aus, dass die Antragstellerin zu 1) sich nicht\nmehr auf die Arbeitsnehmerfreizügigkeit nach § 2 FreizügG/EG berufen könne und unangemessen\nSozialleistungen für sich und die Antragsteller zu 2) und 3) in Anspruch nehme.\n14\nMit Schreiben vom 31. Juli 2018 erhob die Bevollmächtigte der Antragsteller Klage zum Bayerischen\nVerwaltungsgericht München (M 25 K 18.3750) und beantragte zugleich,\n15\n1. die aufschiebende Wirkung der Klage anzuordnen und\n16\n2. den Klägern im Eil- und Klageverfahren Prozesskostenhilfe zu gewähren und Frau Rechtsanwältin … …\nbeizuordnen.\n17\nDie Antragstellerin zu 1) sei freizügigkeitsberechtigt als Arbeitnehmerin. Sie habe sich zeitnah nach ihrer\nEinreise um eine Arbeitsstelle bemüht. Auch eine geringfügige Beschäftigung vermittle das\nArbeitnehmerfreizügigkeitsrecht. Seit Herbst 2016 sei die Antragstellerin zu 1) fast durchgehend\nkrankheitsbedingt arbeitslos. Die Bevollmächtigte der Antragstellerin legte weitere\nArbeitsunfähigkeitsbescheinigungen vor, die folgende Zeiträume umfassen: 23. Mai 2016 - 27. Mai 2016,\n19. September 2016 - 25. September 2016, 28. September - 7. Oktober 2016, 18. Oktober 2016 - 9.\nDezember 2016, 3. Januar 2017 - 15. Januar 2017, 7. März 2017 - 3. April 2017; 30. März 2017 - 9. April\n2017, 2. Mai 2017 - 31. Mai 2017, 2. Juni 2017 - 2. Juli 2017, 7. Juli 2017 - 15. September 2017, 19.\nSeptember 2017 - 15. Oktober 2017, 17. November 2017 - 15. Dezember 2017, 2. Februar 2018 - 15. Juni\n2018, 4. Juni 2018 - 31. August 2018.\n18\nNach der Verbesserung ihres Gesundheitszustandes habe sich die Antragstellerin zu 1) um eine\nArbeitsstelle bemüht. Es liege auch keine unangemessene Inanspruchnahme von Sozialhilfeleistungen vor.\nDie Aufnahme eines Vollzeitjobs sei anfangs nicht möglich gewesen, da die Antragstellerin zu 1) ihre beiden\nKinder betreuen musste. Später sei die Antragstellerin zu 1) auf Grund ihrer Erkrankung arbeitsunfähig und\ndeshalb auf Sozialleistungen angewiesen gewesen.\n19\nDie Antragsgegnerin beantragte mit Schreiben vom 21. August 2018,\n20\nden Antrag abzulehnen.\n21\nWegen der weiteren Einzelheiten des Sachverhalts wird auf die Gerichts- und die beigezogenen\nBehördenakten Bezug genommen.\nII.\nI.\n22\nDer Antrag ist zulässig und begründet.\n23\n1. Der Antrag nach § 80 Abs. 5 VwGO ist zulässig, da auf Grund der Anordnung des Sofortvollzugs nach §\n80 Abs. 2 Nummer 4 VwGO die Klage keine aufschiebende Wirkung hat.\n24\n2. Der Antrag ist auch begründet.\n25\na) Die Anordnung des Sofortvollzugs in Ziff. 6 des Bescheides erfüllt in formaler Hinsicht die\nVoraussetzungen des § 80 Abs. 3 i.V.m. § 80 Abs. 2 Nr. 4 VwGO. Erforderlich ist dabei, dass das\nöffentliche Interesse über jenes Interesse hinausgeht, das den angegriffenen Verwaltungsakts selbst\nrechtfertigt. Diese Anforderung ist umso bedeutsamer, je schwerwiegender die dem Bürger auferlegte\nBelastung ist und je mehr die Maßnahme der Verwaltung Unabänderliches bewirkt. Geeignet zur\nBegründung des Vollzugsinteresses sind dabei auch Umstände wie etwa das Angewiesen sein des\nAusländers auf öffentliche Leistungen zur Deckung des Lebensunterhalts (vgl. OVG Münster B.v. 16.3.2009\n- 18 B 1719/08 - juris). Der Antragsgegnerin war der Ausnahmecharakter des Sofortvollzugs ersichtlich\nbewusst. Der Begründung lässt sich entnehmen, dass sie aus Gründen des zu entscheidenden Einzelfalls\neine sofortige Vollziehung ausnahmsweise für geboten hielt. Die Antragsgegnerin begründet die sofortige\nVollziehung mit dem bisherigen Bezug von Sozialleistungen in unangemessener Höhe und der dadurch\nverursachten Belastung der öffentlichen Kassen. Die Begründung vermag die Anordnung des Sofortvollzugs\nzu tragen.\n26\nb) Nach § 80 Abs. 5 VwGO kann das Gericht der Hauptsache auf Antrag die auf-schiebende Wirkung der\nKlage im Fall des § 80 Abs. 2 Satz 1 Nr. 4 VwGO ganz oder teilweise wiederherstellen. Dabei trifft das\nGericht im Rahmen einer summarischen Prüfung der Sach- und Rechtslage eine eigene, originäre\nErmessensentscheidung unter Abwägung des von der Behörde geltend gemachten Interesses an der\nsofortigen Vollziehung ihres Bescheides und des Interesses des Antragstellers an der aufschiebenden\nWirkung einer Klage. Wesentliches Element dieser Entscheidung sind die Erfolgsaussichten des\nHauptsacheverfahrens. Ergibt die im Rahmen des Verfahrens nach § 80 Abs. 5 VwGO allein erforderliche\nsummarische Prüfung, dass der Rechtsbehelf offensichtlich erfolglos sein wird, tritt das Interesse des\nAntragstellers an der aufschiebenden Wirkung seines Rechtsbehelfs regelmäßig zurück. Erweist sich\ndagegen der angefochtene Bescheid bei kursorischer Prüfung als offensichtlich rechtswidrig, besteht kein\nInteresse an dessen sofortiger Vollziehung. Ist der Ausgang des Hauptsacheverfahrens nicht hinreichend\nabsehbar, bleibt es bei einer allgemeinen Interessenabwägung.\n27\nNach der im Verfahren des § 80 Abs. 5 VwGO gebotenen summarischen Prüfung erweist sich die Klage\naller Voraussicht nach als begründet.\n28\nDie Voraussetzungen für eine Verlustfeststellung nach § 5 Abs. 4 Satz 1 FreizügG/EU liegen nicht vor.\nDanach kann der Verlust des Freizügigkeitsrechts nach § 2 Abs. 1 FreizügG/EU festgestellt werden, wenn\ndie Voraussetzungen des Rechts nach § 2 Abs. 1 FreizügG/EU innerhalb von 5 Jahren nach Begründung\ndes ständigen rechtmäßigen Aufenthalts im Bundesgebiet entfallen sind, (von Anfang an) nicht vorliegen\n(BVerwG U.v. 16.7.2015 - 1 C 22/14 - juris Rn. 15) oder sich die Berufung auf die Arbeitnehmerfreizügigkeit\nals rechtsmissbräuchlich erweist.\n29\nDie Antragstellerin zu 1) ist jedenfalls aktuell nach § 2 Abs. 2 FreizügG/EU freizügigkeitsberechtigt.\nMaßgeblich für die rechtliche Beurteilung der Feststellung des Nichtbestehens/Bestehens des\nFreizügigkeitsrechts ist grundsätzlich die Sach- und Rechtslage im Zeitpunkt der letzten mündlichen\nVerhandlung oder Entscheidung des Tatsachengerichts (BVerwG U.v. 16. Juli 2015 - 1 C 22/14 - juris Rn.\n11).\n30\nDie Antragstellerin zu 1) geht seit 1. Dezember 2018 einer sozialversicherungspflichtigen Tätigkeit als\nPflegekraft/Seniorenbetreuerin in Vollzeit nach. Damit ist sie § 2 Abs. 2 Nummer 1 FreizügG/EU aktuell\nfreizügigkeitsberechtigt als Arbeitnehmerin.\n31\nDie Berufung auf die Freizügigkeitsberechtigung als Arbeitnehmerin nach § 2 Abs. 2 Nummer 1\nFreizügG/EU stellt sich nach summarischer Prüfung auch nicht als rechtsmissbräuchlich dar. Nach\nständiger Rechtsprechung des Europäischen Gerichtshofs findet Unionsrecht bei rechtsmissbräuchlichen\nPraktiken keine Anwendung (EuGH U.v. 12.3.2014 - C-456/12, O. und B. - Juris Rn. 58 m.w.N.). Eine\nBerufung auf die Freizügigkeitsberechtigung stellt sich dann als rechtsmissbräuchlich heraus, wenn die\nGesamtwürdigung der objektiven Umstände ergibt, dass trotz formaler Einhaltung der unionsrechtlichen\nBedingungen das Ziel der Regelung nicht erreicht wurde, und dass zum anderen ein subjektives Element\nvorliegt, nämlich die Absicht, sich einen unionrechtlich vorgesehenen Vorteil dadurch zu verschaffen, dass\ndie entsprechenden Voraussetzungen willkürlich geschaffen werden. Dies betrifft zum Beispiel Fälle, in\ndenen der Betreffende zwar formal die unionsrechtlichen Voraussetzungen für die Arbeitnehmerfreizügigkeit\nerfüllt, aber von vornherein nicht die Absicht hat, für die Dauer des Aufenthalts eine Erwerbstätigkeit\nauszuüben, die ausreichende Existenzmittel sichert.\n32\nVorliegend mag die (Wieder-)Aufnahme der Erwerbstätigkeit zum 1. Dezember 2018 in Vollzeit auch unter\ndem Eindruck der Verlusterklärung der Antragsgegnerin stehen. Jedoch ergibt sich unter Berücksichtigung\nder objektiven Gesamtumstände des Einzelfalls, dass diese Arbeitsaufnahme nicht als rechtsmissbräuchlich\nanzusehen sein dürfte. Denn die im einstweiligen Rechtsschutzverfahren gebotene summarische Prüfung\nergibt, dass die Antragstellerin zu 1) über den gesamten Zeitraum seit ihrer Einreise freizügigkeitsberechtigt\nals Arbeitnehmerin nach § 2 Abs. 2 Nr. 1 und 1a FreizügG/EU war.\n33\nDie Antragstellerin zu 1) ist im Juli 2014 eingereist und nahm im November 2014, nach der Trennung vom\nVater ihres 2. Kindes, eine geringfügige Beschäftigung als Reinigungskraft auf. Nach dem weit\nauszulegenden Begriff des Arbeitnehmers nach Art. 45 AEUV ist als Arbeitnehmer jeder anzusehen, der\neine tatsächliche und echte Tätigkeit ausübt. Dabei schließt auch der Umstand, dass im Rahmen des\nBeschäftigungsverhältnisses nur weniger Arbeitsstunden geleistet werden, die Arbeitnehmereigenschaft\nnicht zwangsläufig aus. Neben der Arbeitszeit und Vergütung spielen beispielsweise auch Aspekte wie der\nAnspruch auf bezahlten Urlaub, die Geltung von Lohnfortzahlung im Krankheitsfall, die Anwendung des\nTarifvertrages oder auch die Dauer des Beschäftigungsverhältnisses eine Rolle (EuGH U.v. 12.3.2014 - C-\n456/12 O. und B. - juris Rn. 58). Aus dem vorgelegten Arbeitsvertrag ergibt sich, dass es sich um einen auf\n2 Jahre befristeten Minijob handelte, bei dem Tariflohn gezahlt wurde, ein Urlaubsanspruch bestand und\nauch die Entgeltfortzahlung im Krankheitsfall nicht ausgeschlossen war. Die Antragstellerin hat dann zum 1.\nJuni 2015 eine weitere Tätigkeit als Reinigungskraft in einem Umfang von 30 Stunden wöchentlich\nangetreten. Das Arbeitsverhältnis wurde durch Kündigung des Arbeitgebers zum 24. Juli 2015 wegen\nWegfall des Arbeitsplatzes beendet. Mit Aktenvermerk vom 14. Juli 2015 stellte die Antragsgegnerin fest,\ndass die Antragstellerin freizügigkeitsberechtigt ist, obwohl die Antragstellerin zu diesem Zeitpunkt bereits\nergänzend Sozialhilfeleistungen bezogen hat. Am 20. Juli 2015 nahm die Antragstellerin einen weiteren Job\nals Haushaltshilfe in einem Privathaushalt als Minijob auf, den sie bis 10. März 2016 ausübte. Im Anschluss\ndaran arbeitete sie bei der Firma Enzian Clean Service bis 7. Oktober 2016 in Vollzeit. Das Arbeitsverhältnis\nwurde nach Verlängerung der Probezeit in der Probezeit auf Grund krankheitsbedingter Fehlzeiten\ngekündigt. Danach hat die Antragstellerin erst wieder im Dezember 2018 gearbeitet. Aus den obigen\nAusführungen ergibt sich, dass die Antragstellerin zu 1) in der Zeit von 2014 bis 2016 durchgehend\ngearbeitet hat. Da sich unter den Arbeitsverhältnissen Vollzeitstellen bzw. Teilzeitstellen in einem größeren\nZeitumfang befinden, kann jedenfalls im Verfahren des einstweiligen Rechtsschutzes nicht ohne Weiteres\ndavon ausgegangen werden, dass sich die Antragstellerin zu 1) nur in der Bundesrepublik Deutschland\nbefindet, um Sozialhilfeleistungen zu beziehen.\n34\nEs spricht viel dafür, dass die Antragstellerin zu 1) ihr Arbeitnehmer-Freizügigkeitsrecht in der Zeit von\nHerbst 2016 bis Herbst 2018 auch nicht verloren hat. Das Recht auf Freizügigkeit bleibt für Arbeitnehmer\nbei vorübergehender Erwerbsminderung infolge Krankheit oder Unfall (§ 2 Abs. 3 Satz 1 Nummer 1\nFreizügG/EU) selbst dann unberührt, wenn das Arbeitsverhältnis nicht mehr besteht. Dies ergibt sich zum\neinen aus Art. 17 Absatz 1 Satz 2 RL 2004/38/EG, wonach Zeiten unfreiwilliger Arbeitslosigkeit als Zeiten\nder Erwerbstätigkeit gelten. Da der Richtliniengeber die Zeiten unfreiwilliger Arbeitslosigkeit mit krankheitsoder\nunfallbedingten Fehlzeiten gleichgestellt hat, ist davon auszugehen, dass das Bestehen eines\nArbeitsverhältnisses nicht voraussetzend für die „Fiktionswirkung“ des § 2 Abs. 3 Satz 1 Nummer 1\nFreizügG/EU ist (BayVGH U.v. 28.7.2017 - 10 B 17.339). Die Klägerin war fast im gesamten Zeitraum von\nHerbst 2016 bis August 2018 ausweislich der vorgelegten Bescheinigungen u.a. auf Grund einer\nSchulterverletzung arbeitsunfähig. Eine dauerhafte Erwerbsunfähigkeit wurde nicht bescheinigt.\nInsbesondere aus dem amtsärztlichen Gutachten der Stadt Ingolstadt vom 30. April 2018 zur Beurteilung\nder Arbeits-/Erwerbsfähigkeit der Antragstellerin geht hervor, dass die Antragstellerin täglich zwischen 3 und\n6 Stunden leichte Tätigkeiten (stehend, gehend, sitzend) verrichten kann. Häufiges Bücken, häufiges Heben\nund Tragen ohne mechanische Mittel sowie Zwangshaltungen seien zu vermeiden. Die Antragstellerin zu 1)\nleide an einer Erkrankung des Bewegungsapparates, die nicht vollständig heilbar sei. Deswegen leide sie\nbei den meisten Bewegungen unter starken Schmerzen. Sie sei in kontinuierlicher orthopädischer und\nneurochirurgischer Behandlung und zeige viel Eigeninitiative, um ihre Beschwerden zu lindern. Es\nbestünden noch ein paar Behandlungsoptionen, die eine Steigerung der Arbeitsfähigkeit bewirken können.\nSomit bleibe abzuwarten, wie sich das Beschwerdebild unter den angestrebten Therapien verändere. Es\nbestehe eine gute Arbeitsmotivation, deshalb sei die Prognose positiv. Für die nächsten 6 Monate sei die\nLeistungsfähigkeit vermindert. Da die Antragstellerin zu 1) nur vorübergehend arbeitsunfähig war, bleibt ihr\ndie Arbeitnehmerfreizügigkeit trotz Verlusts ihrer Arbeitsstelle nach § 2 Abs. 3 Nummer 1 FreizügG/EU\nerhalten.\n35\nFür die Zeit danach ergibt sich für die Antragstellerin zu 1) ein Freizügigkeitsrecht nach § 2 Abs. 2 Nummer\n1a FreizügG/EU als arbeitssuchend. Entsprechende Bewerbungen wurden von der Antragstellerin zu 1)\nvorgelegt.\n36\nBei der vorliegenden Erwerbsbiografie ist bei der Gesamtwürdigung der objektiven Umstände ebenfalls zu\nberücksichtigen, dass die Antragstellerin zu 1) zunächst keine Vollzeitarbeit auf Grund der\nBetreuungssituation ihrer Kinder und der Erkrankung des Antragstellers zu 2) aufnehmen konnte. Vor\ndiesem Hintergrund kann derzeit nicht davon ausgegangen werden, dass die Antragstellerin zu 1) von\nvornherein die Absicht hatte, lediglich einzureisen, um Sozialhilfe zu beziehen.\n37\nEine solche Absicht kann auch nicht aus der Höhe der bisher aufgewendeten Sozialhilfebeträge\nangenommen werden. Zwar beziehen die Antragsteller seit November 2014 Sozialhilfe und später\nzusätzlich Jugendhilfe i.H.v. insgesamt rund 200.000 EUR. Diese Kosten übersteigen um ein vielfaches\ndasjenige, was ein durchschnittlicher Arbeitnehmer bei einer Vollzeitarbeit mit zwei unterhaltspflichtigen\nKindern erwirtschaften kann. Der höchste Anteil an den Kosten ist durch die stationäre Unterbringung des\nAntragstellers zu 2) verursacht, nämlich 4.500,- bzw. 5.500,- Euro monatlich. Die Unterbringung begann\nzwei Jahre nach Einreise der Antragsteller und war für die Antragsteller auch nicht absehbar. Es ist nicht\nersichtlich, dass die Antragsteller bei ihrer Einreise auf eine solche Unterbringung auf Kosten der\nAllgemeinheit hingearbeitet hätten. Im Übrigen erfolgte sowohl die stationäre Unterbringung des\nAntragstellers zu 2) als auch die Einrichtung einer Familienhilfe unabhängig davon, ob die Antragstellerin zu\n1) ihren Lebensunterhalt sichern kann oder nicht. Es ist auch fraglich, ob es sich bei den Kosten der\nJugendhilfe um Kosten der Sozialhilfe i.S.d. des Unionsrechts handelt, da es sich nicht um Kosten der\nExistenzsicherung handelt. Die Jugendhilfe verfolgt vielmehr das Ziel, jeden jungen Menschen in seiner\nEntwicklung zu fördern und ihn in seiner Entwicklung zu einer eigenverantwortlichen und\ngemeinschaftsfähigen Person zu unterstützen (vgl. § 1 Abs. 1 SGB VIII).\n38\nNach alledem kann vorläufig nicht davon ausgegangen werden, dass die Antragsteller nur zu dem Zweck\neingereist sind, Sozialhilfe zu beziehen.\n39\nAllein der Umstand des Sozialhilfebezuges führt nicht zum Verlust des Arbeitnehmerfreizügigkeitsrechts.\nDenn aus Art. 24 Abs. 1 RL 2004/38 EG ergibt sich, dass jeder Unionsbürger ein Recht auf\nGleichbehandlung mit den Staatsangehörigen des Mitgliedstaates genießt. Nach Art. 24 Abs. 2 RL 2004/38\nist der Mitgliedstaat lediglich berechtigt, u.a. Personen, die keine Arbeitnehmer sind, und deren\nFamilienangehörigen den Anspruch auf Sozialhilfe einzuschränken. Dies ergibt sich aus dem 16.\nErwägungsgrund der Richtlinie.\n40\nDer am 1. September 2002 geborene Antragsteller zu 2) und der am 31. Dezember 2012 geborene\nAntragsteller zu 3) leiten als minderjähriges Kind bzw. Kind unter 21 Jahren ihr Freizügigkeitsrecht als\nFamilienangehörige der Antragstellerin zu 1) aus § 3 Abs. 2 Nummer 1 FreizügG/EU ab.\nII.\n41\nDie Kostentragung ergibt sich aus § 154 Abs. 1 VwGO.\nIII.\n42\nDie Streitwertfestsetzung beruht auf § 53 Abs. 2 Nr. 2, § 52 Abs. 2 GKG in Verbindung mit Nrn. 1.1.3 und\n1.5. des Streitwertkatalogs der Verwaltungsgerichtsbarkeit.\nIV.\n43\nAuf Grund der Erfolgsaussichten der Klage und des Antrags sowie des Umstandes, dass die Antragsteller\nausweislich der Erklärung über die persönlichen und wirtschaftlichen Verhältnisse die Kosten der\nProzessführung nicht aufbringen können, war den Antragstellern und Klägern Prozesskostenhilfe zu\ngewähren, § 166 Abs. 1, §§ 114 ff. ZPO.\n\n"
}